ankdown/__init__.py
ankdown/ankdown.py
ankdown/highlight.css
ankdown-0.7.1.dist-info/LICENSE
ankdown-0.7.1.dist-info/METADATA
ankdown-0.7.1.dist-info/WHEEL
ankdown-0.7.1.dist-info/entry_points.txt
ankdown-0.7.1.dist-info/top_level.txt
ankdown-0.7.1.dist-info/RECORD
