Metadata-Version: 2.1
Name: ankdown
Version: 0.7.1
Summary: A utility for converting Markdown into Anki cards
Home-page: https://github.com/benwr/ankdown
Author: Ben Weinstein-Raun
Author-email: b@w-r.me
License: MIT
Keywords: anki spaced-repetition markdown math latex
Platform: UNKNOWN
Classifier: Development Status :: 3 - Alpha
Classifier: Intended Audience :: Developers
Classifier: Topic :: Education :: Computer Aided Instruction (CAI)
Classifier: License :: OSI Approved :: MIT License
Classifier: Programming Language :: Python :: 3
Classifier: Programming Language :: Python :: 3.0
Classifier: Programming Language :: Python :: 3.1
Classifier: Programming Language :: Python :: 3.2
Classifier: Programming Language :: Python :: 3.3
Classifier: Programming Language :: Python :: 3.4
Classifier: Programming Language :: Python :: 3.5
Classifier: Programming Language :: Python :: 3.6
Classifier: Programming Language :: Python :: 3.7
Classifier: Programming Language :: Python :: 3 :: Only
Requires-Dist: genanki (>=0.6.3)
Requires-Dist: misaka (>=2.1.0)
Requires-Dist: docopt (>=0.6.2)
Requires-Dist: houdini.py (>=0.1.0)
Requires-Dist: Pygments (>=2.4.0)
